keras/__init__.py
keras/activations.py
keras/callbacks.py
keras/constraints.py
keras/initializations.py
keras/metrics.py
keras/models.py
keras/objectives.py
keras/optimizers.py
keras/regularizers.py
keras/applications/__init__.py
keras/applications/audio_conv_utils.py
keras/applications/imagenet_utils.py
keras/applications/inception_v3.py
keras/applications/music_tagger_crnn.py
keras/applications/resnet50.py
keras/applications/vgg16.py
keras/applications/vgg19.py
keras/applications/xception.py
keras/backend/__init__.py
keras/backend/common.py
keras/backend/mxnet_backend.py
keras/backend/tensorflow_backend.py
keras/backend/theano_backend.py
keras/datasets/__init__.py
keras/datasets/cifar.py
keras/datasets/cifar10.py
keras/datasets/cifar100.py
keras/datasets/imdb.py
keras/datasets/mnist.py
keras/datasets/reuters.py
keras/engine/__init__.py
keras/engine/topology.py
keras/engine/training.py
keras/layers/__init__.py
keras/layers/advanced_activations.py
keras/layers/convolutional.py
keras/layers/convolutional_recurrent.py
keras/layers/core.py
keras/layers/embeddings.py
keras/layers/local.py
keras/layers/noise.py
keras/layers/normalization.py
keras/layers/pooling.py
keras/layers/recurrent.py
keras/layers/wrappers.py
keras/preprocessing/__init__.py
keras/preprocessing/image.py
keras/preprocessing/sequence.py
keras/preprocessing/text.py
keras/utils/__init__.py
keras/utils/data_utils.py
keras/utils/generic_utils.py
keras/utils/io_utils.py
keras/utils/layer_utils.py
keras/utils/np_utils.py
keras/utils/test_utils.py
keras/utils/visualize_util.py
keras/wrappers/__init__.py
keras/wrappers/scikit_learn.py
keras_mxnet_skm-1.2.2.1.dist-info/DESCRIPTION.rst
keras_mxnet_skm-1.2.2.1.dist-info/METADATA
keras_mxnet_skm-1.2.2.1.dist-info/RECORD
keras_mxnet_skm-1.2.2.1.dist-info/WHEEL
keras_mxnet_skm-1.2.2.1.dist-info/metadata.json
keras_mxnet_skm-1.2.2.1.dist-info/top_level.txt
