Metadata-Version: 2.0
Name: keras-mxnet-skm
Version: 1.2.2.1
Summary: Deep Learning for Python. Keras with highly scalable, high performant Apache MXNet backend support.
Home-page: https://github.com/dmlc/keras
License: MIT
Platform: UNKNOWN
Provides-Extra: h5py
Provides-Extra: tests
Provides-Extra: visualize
Requires-Dist: theano
Requires-Dist: pyyaml
Requires-Dist: six
Provides-Extra: h5py
Requires-Dist: h5py; extra == 'h5py'
Provides-Extra: tests
Requires-Dist: pytest; extra == 'tests'
Requires-Dist: pytest-cov; extra == 'tests'
Requires-Dist: pytest-pep8; extra == 'tests'
Requires-Dist: pytest-xdist; extra == 'tests'
Requires-Dist: python-coveralls; extra == 'tests'
Requires-Dist: coverage (==3.7.1); extra == 'tests'
Provides-Extra: visualize
Requires-Dist: pydot-ng; extra == 'visualize'
